python3_pip_skeleton/__init__.py
python3_pip_skeleton/__main__.py
python3_pip_skeleton/_version.py
python3_pip_skeleton-3.5.0.dist-info/LICENSE
python3_pip_skeleton-3.5.0.dist-info/METADATA
python3_pip_skeleton-3.5.0.dist-info/WHEEL
python3_pip_skeleton-3.5.0.dist-info/entry_points.txt
python3_pip_skeleton-3.5.0.dist-info/top_level.txt
python3_pip_skeleton-3.5.0.dist-info/RECORD
